inventory_analysis/__init__.py
inventory_analysis/date_hsw.py
inventory_analysis/week_formats.py
inventory_analysis-0.0.11.dist-info/LICENSE
inventory_analysis-0.0.11.dist-info/METADATA
inventory_analysis-0.0.11.dist-info/WHEEL
inventory_analysis-0.0.11.dist-info/top_level.txt
inventory_analysis-0.0.11.dist-info/RECORD
