Metadata-Version: 2.1
Name: inventory-analysis
Version: 0.0.11
Summary: Inventory Analysis package
Home-page: https://github.com/ivanvallenas/inventory-analysis
Author: Ivan Vallenas
Author-email: <ivan.vallenas.munoz@gmail.com>
License: UNKNOWN
Platform: UNKNOWN
License-File: LICENSE
